saturn_lib/__init__.py
saturn_lib/abstractBase.py
saturn_lib/clsViTDetection.py
saturn_lib/csraClassify.py
saturn_lib/fasterDetectionPyTorch.py
saturn_lib/vggClassify.py
saturn_lib/yolov5Detection.py
saturn_lib/csra_libs/__init__.py
saturn_lib/viT_libs/vit_model.py
saturn_lib/yolov5_libs/__init__.py
saturn_lib/yolov5_libs/activations.py
saturn_lib/yolov5_libs/autoanchor.py
saturn_lib/yolov5_libs/datasets.py
saturn_lib/yolov5_libs/general.py
saturn_lib/yolov5_libs/google_utils.py
saturn_lib/yolov5_libs/loss.py
saturn_lib/yolov5_libs/metrics.py
saturn_lib/yolov5_libs/plots.py
saturn_lib/yolov5_libs/torch_utils.py
saturn_lib/yolov5_libs/models/__init__.py
saturn_lib/yolov5_libs/models/common.py
saturn_lib/yolov5_libs/models/experimental.py
saturn_lib/yolov5_libs/models/export.py
saturn_lib/yolov5_libs/models/yolo.py
saturn_lib/yolov5_libs/models/yolov5l.yaml
saturn_lib/yolov5_libs/models/yolov5m.yaml
saturn_lib/yolov5_libs/models/yolov5s.yaml
saturn_lib/yolov5_libs/models/yolov5x.yaml
saturn_lib-0.0.11.dist-info/METADATA
saturn_lib-0.0.11.dist-info/WHEEL
saturn_lib-0.0.11.dist-info/top_level.txt
saturn_lib-0.0.11.dist-info/RECORD
