Metadata-Version: 2.1
Name: saturn-lib
Version: 0.0.11
Summary: a dete lib for TXKJ algo
Home-page: https://github.com/newjokker/JoUtil.git
Author: jokker
Author-email: 18761609908@163.com
License: UNKNOWN
Platform: UNKNOWN
Requires: numpy
Requires: pillow
Requires: pandas
Requires: easydict
Requires: matplotlib
Requires: imagehash
Requires: prettytable
Requires: progress
Requires: progressbar
Requires: requests
Requires: imageio
Requires: pyexiv2
Requires: cv2
Requires: exifread
Requires: whatimage
Requires: pyheif
Requires: pymysql
Requires: pytesseract
Requires: beautifulsoup4
Requires: Crypto
Requires: flask
